url_param_sorted/__init__.py
url_param_sorted-0.0.2.data/scripts/url-param-sorted
url_param_sorted-0.0.2.dist-info/LICENSE
url_param_sorted-0.0.2.dist-info/METADATA
url_param_sorted-0.0.2.dist-info/WHEEL
url_param_sorted-0.0.2.dist-info/top_level.txt
url_param_sorted-0.0.2.dist-info/RECORD
