Metadata-Version: 2.1
Name: url-param-sorted
Version: 0.0.2
Summary: url-param-sorted - предоставляет функцию для cортировки параметров url в порядке их возрастания
Home-page: https://github.com/darviarush/python-url-param-sorted
Author: Kosmina O. Yaroslav
Author-email: darviarush@mail.ru
License: MIT
Platform: any
Classifier: Development Status :: 5 - Production/Stable
Classifier: Topic :: Text Processing
Classifier: License :: OSI Approved :: MIT License
Classifier: Operating System :: OS Independent
Classifier: Programming Language :: Python :: 3
Classifier: Programming Language :: Python :: 3.3
Classifier: Programming Language :: Python :: 3.4
Classifier: Programming Language :: Python :: 3.5
Classifier: Programming Language :: Python :: 3.6
Classifier: Programming Language :: Python :: 3.7
Requires-Python: >=3.6
